{
	"info": {
		"_postman_id": "0b9bcb53-2d64-45b9-89af-66f48aff3c1c",
		"name": "Lenra Server",
		"description": "This document will show you how to authentificate (Oauth2) and interact with the Lenra server API using Postman's VSCode extension.",
		"schema": "https://schema.getpostman.com/json/collection/v2.1.0/collection.json",
		"_exporter_id": "6750074"
	},
	"item": [
		{
			"name": "Authentification",
			"item": [
				{
					"name": "login_with_authorization_code",
					"event": [
						{
							"listen": "test",
							"script": {
								"exec": [
									"pm.test(\"Status code is 200\", function () {\r",
									"    pm.response.to.have.status(200);\r",
									"});\r",
									"\r",
									"pm.test(\"Has access_token\", function () {\r",
									"    var jsonData = pm.response.json();\r",
									"    pm.expect(jsonData.access_token, \"Request didn't reply an access token\").to.exist\r",
									"    pm.collectionVariables.set(\"lenra_access_token\", jsonData.access_token);\r",
									"});\r",
									"\r",
									"    \r",
									"\r",
									""
								],
								"type": "text/javascript"
							}
						}
					],
					"request": {
						"method": "POST",
						"header": [
							{
								"name": "cache-control",
								"sortOrder": 2,
								"infoTitle": "We recommend using this header",
								"info": "Postman added \"Cache-Control: no-cache\" as a precautionary measure to prevent the server from returning stale response when one makes repeated requests.\n\nYou can remove this header in the app settings or enter a new one with a different value.",
								"allowedToToggle": false,
								"disableEdit": true,
								"previewSettingsLink": "Go to settings",
								"key": "Cache-Control",
								"value": "no-cache",
								"system": true,
								"type": "text"
							},
							{
								"name": "postman-token",
								"sortOrder": 3,
								"infoTitle": "We recommend using this header",
								"info": "The Postman-Token header appends a random UUID to every outgoing request. Postman adds this header for API developers to better debug requests sent and to ensure separate requests appear distinct to the receiving server.\n\nYou can remove this header in the app settings.",
								"allowedToToggle": false,
								"disableEdit": true,
								"previewSettingsLink": "Go to settings",
								"key": "Postman-Token",
								"value": "<calculated when request is sent>",
								"system": true,
								"type": "text"
							},
							{
								"name": "content-type",
								"sortOrder": 4,
								"infoTitle": "This header was automatically added",
								"info": "The Content-Type header is added to help the server identify the media type of the request body that is present in this request.\n\nUse the request body tab to control the value or to remove this header.",
								"allowedToToggle": true,
								"disableEdit": true,
								"previewSettingsLink": "Go to body",
								"key": "Content-Type",
								"value": "application/x-www-form-urlencoded",
								"system": true,
								"type": "text"
							},
							{
								"name": "content-length",
								"sortOrder": 5,
								"infoTitle": "This header was automatically added",
								"info": "The Content-Length header was added to indicate to the server the size of the request body that is added to this request. Server uses this value to parse the request body accurately.\n\nYou can remove the header or enter a new one with a different value.",
								"allowedToToggle": true,
								"disableEdit": true,
								"previewSettingsLink": "Go to body",
								"key": "Content-Length",
								"value": "<calculated when request is sent>",
								"system": true,
								"type": "text"
							},
							{
								"name": "host",
								"sortOrder": 6,
								"infoTitle": "We recommend using this header",
								"info": "The Host header is added to identify the domain name for which a request is being sent to the server. This header is implicitly sent by every HTTP client.\n\nYou can remove the header or enter a new one with a different value. It is most likely that without this header, your request will return an HTTP 400 error.",
								"allowedToToggle": true,
								"disableEdit": true,
								"key": "Host",
								"value": "<calculated when request is sent>",
								"system": true,
								"type": "text"
							},
							{
								"name": "user-agent",
								"sortOrder": 7,
								"infoTitle": "We recommend using this header",
								"info": "The User-Agent header is added to help the server identify Postman as the HTTP requesting application or client.\n\nIt is recommended that this header be sent, but you can remove the header or enter a new one with a different value.",
								"allowedToToggle": true,
								"disableEdit": true,
								"key": "User-Agent",
								"value": "PostmanRuntime/7.32.1",
								"system": true,
								"type": "text"
							},
							{
								"name": "accept",
								"sortOrder": 8,
								"infoTitle": "We recommend using this header",
								"info": "The \"Accept: */*\" header is added to tell the server that Postman can understand and process all forms of response content types.\n\nIt is recommended that this header be sent, but you can remove the header or enter a new one with a different value.",
								"allowedToToggle": true,
								"disableEdit": true,
								"key": "Accept",
								"value": "*/*",
								"system": true,
								"type": "text"
							},
							{
								"name": "accept-encoding",
								"sortOrder": 9,
								"infoTitle": "We recommend using this header",
								"info": "The Accept-Encoding header is added to indicate to the server that Postman HTTP client supports a defined list of content-encoding or compression algorithms as response.\n\nYou can remove the header or enter a new one with a different value. Doing that may not accurately render the response within the app.",
								"allowedToToggle": true,
								"disableEdit": true,
								"key": "Accept-Encoding",
								"value": "gzip, deflate, br",
								"system": true,
								"type": "text"
							},
							{
								"name": "connection",
								"sortOrder": 10,
								"infoTitle": "We recommend using this header",
								"info": "Postman added the Connection header to indicate the server to keep the underlying network connection open once the current response is received. This allows Postman to reuse the same connection for faster response times in subsequent requests to the same server.\n\nYou can remove this header or enter a new one with a different value, such as `Connection: Close` to control this behaviour.",
								"allowedToToggle": true,
								"disableEdit": true,
								"key": "Connection",
								"value": "keep-alive",
								"system": true,
								"type": "text"
							},
							{
								"key": "Content-Type",
								"value": "application/x-www-form-urlencoded",
								"type": "text",
								"id": 0
							}
						],
						"body": {
							"mode": "urlencoded",
							"urlencoded": [
								{
									"key": "grant_type",
									"value": "authorization_code",
									"type": "text"
								},
								{
									"key": "code",
									"value": "{{hydra_auth_code}}",
									"type": "text"
								},
								{
									"key": "client_id",
									"value": "{{lenra_client_id}}",
									"type": "text"
								},
								{
									"key": "redirect_uri",
									"value": "{{hydra_redirect_url}}",
									"type": "text"
								},
								{
									"key": "state",
									"value": "p1z8pm12ov",
									"type": "text"
								}
							]
						},
						"url": {
							"raw": "{{hydra_endpoint}}/oauth2/token",
							"host": [
								"{{hydra_endpoint}}"
							],
							"path": [
								"oauth2",
								"token"
							]
						},
						"description": "# Authentification\n\nThe"
					},
					"response": []
				}
			],
			"description": "To get your authentification token, you'll need to get you're authentification code from the OAuth process.\n\nTo get it, you'll need to register a new Oauth client for the [oauthdebugger](https://oauthdebugger.com/), go to your terminal in the Lenra Server project directory and run the following command :\n\n``` bash\n# Run the local dependencies to have hydra and postgres running\n~ $ docker compose up -d\n ✔ Network server_default            Created                                                                                     0.1s \n ✔ Container lenra-mongo             Started                                                                                     0.1s \n ✔ Container server-hydra-migrate-1  Started                                                                                     0.1s \n ✔ Container lenra-postgres          Started                                                                                     0.1s \n ✔ Container server-hydra-1          Started                                                                                     0.0s \n# Add a new Oauth2 Client for oauthdebugger.com\n~ $ mix create_oauth2_client backoffice --redirect-uri https://oauthdebugger.com/debug\n09:42:09.243 [debug] Create hydra client %{allowed_cors_origins: [\"http://localhost:10000\"], client_name: \"Lenra Backoffice\", redirect_uris: [\"https://oauthdebugger.com/debug\"], scope: \"profile store manage:account manage:apps\", skip_consent: false, token_endpoint_auth_method: \"none\"}\nOauth client backoffice :\n%{\n  \"allowed_cors_origins\" => [\"http://localhost:10000\"],\n  \"client_id\" => \"5fbecdf6-ad85-4aea-870e-26a45fe90791\",\n  \"client_name\" => \"Lenra Backoffice\",\n  \"metadata\" => %{},\n  \"redirect_uris\" => [\"https://oauthdebugger.com/debug\"],\n  \"scope\" => \"profile store manage:account manage:apps\"\n}\n\n ```\n\nJust copy the \\`client_id\\` and go to [oauthdebugger](https://oauthdebugger.com/), fill the form with following informations :\n\n- Authorize URI: [http://localhost:4444/oauth2/auth](http://localhost:4444/oauth2/auth)\n- Redirect URI: [https://oauthdebugger.com/debug](https://oauthdebugger.com/debug)\n- Client ID: 5fbecdf6-ad85-4aea-870e-26a45fe907917\n- Scope: profile store manage:account manage:apps\n- Response type: code\n- Response mode: form_post\n    \n\nLet everything else in the default value.\n\nStart the server with the following command :\n\n``` bash\n~ $ mix phx.server\n\n ```\n\nAnd then you can change the LenraClientAuthCode in the Globals Environment from the Postman's extension tabs."
		},
		{
			"name": "Apps",
			"item": [
				{
					"name": "current_user_list_app",
					"event": [
						{
							"listen": "test",
							"script": {
								"exec": [
									"pm.test(\"Status code is 200\", function () {\r",
									"    pm.response.to.have.status(200);\r",
									"});\r",
									"\r",
									"pm.test(\"Has some apps\", function () {\r",
									"    var jsonData = pm.response.json();\r",
									"    pm.expect(jsonData).to.be.an(\"array\")\r",
									"    const last_app = jsonData.last()\r",
									"    pm.expect(last_app).not.to.be.an(\"undefined\");\r",
									"    pm.collectionVariables.set(\"lenra_latest_created_app\", last_app.id);\r",
									"});\r",
									""
								],
								"type": "text/javascript"
							}
						}
					],
					"request": {
						"method": "GET",
						"header": [
							{
								"name": "cache-control",
								"sortOrder": 2,
								"infoTitle": "We recommend using this header",
								"info": "Postman added \"Cache-Control: no-cache\" as a precautionary measure to prevent the server from returning stale response when one makes repeated requests.\n\nYou can remove this header in the app settings or enter a new one with a different value.",
								"allowedToToggle": false,
								"disableEdit": true,
								"previewSettingsLink": "Go to settings",
								"key": "Cache-Control",
								"value": "no-cache",
								"system": true,
								"type": "text"
							},
							{
								"name": "postman-token",
								"sortOrder": 3,
								"infoTitle": "We recommend using this header",
								"info": "The Postman-Token header appends a random UUID to every outgoing request. Postman adds this header for API developers to better debug requests sent and to ensure separate requests appear distinct to the receiving server.\n\nYou can remove this header in the app settings.",
								"allowedToToggle": false,
								"disableEdit": true,
								"previewSettingsLink": "Go to settings",
								"key": "Postman-Token",
								"value": "<calculated when request is sent>",
								"system": true,
								"type": "text"
							},
							{
								"name": "host",
								"sortOrder": 6,
								"infoTitle": "We recommend using this header",
								"info": "The Host header is added to identify the domain name for which a request is being sent to the server. This header is implicitly sent by every HTTP client.\n\nYou can remove the header or enter a new one with a different value. It is most likely that without this header, your request will return an HTTP 400 error.",
								"allowedToToggle": true,
								"disableEdit": true,
								"key": "Host",
								"value": "<calculated when request is sent>",
								"system": true,
								"type": "text"
							},
							{
								"name": "user-agent",
								"sortOrder": 7,
								"infoTitle": "We recommend using this header",
								"info": "The User-Agent header is added to help the server identify Postman as the HTTP requesting application or client.\n\nIt is recommended that this header be sent, but you can remove the header or enter a new one with a different value.",
								"allowedToToggle": true,
								"disableEdit": true,
								"key": "User-Agent",
								"value": "PostmanRuntime/7.32.1",
								"system": true,
								"type": "text"
							},
							{
								"name": "accept",
								"sortOrder": 8,
								"infoTitle": "We recommend using this header",
								"info": "The \"Accept: */*\" header is added to tell the server that Postman can understand and process all forms of response content types.\n\nIt is recommended that this header be sent, but you can remove the header or enter a new one with a different value.",
								"allowedToToggle": true,
								"disableEdit": true,
								"key": "Accept",
								"value": "*/*",
								"system": true,
								"type": "text"
							},
							{
								"name": "accept-encoding",
								"sortOrder": 9,
								"infoTitle": "We recommend using this header",
								"info": "The Accept-Encoding header is added to indicate to the server that Postman HTTP client supports a defined list of content-encoding or compression algorithms as response.\n\nYou can remove the header or enter a new one with a different value. Doing that may not accurately render the response within the app.",
								"allowedToToggle": true,
								"disableEdit": true,
								"key": "Accept-Encoding",
								"value": "gzip, deflate, br",
								"system": true,
								"type": "text"
							},
							{
								"name": "connection",
								"sortOrder": 10,
								"infoTitle": "We recommend using this header",
								"info": "Postman added the Connection header to indicate the server to keep the underlying network connection open once the current response is received. This allows Postman to reuse the same connection for faster response times in subsequent requests to the same server.\n\nYou can remove this header or enter a new one with a different value, such as `Connection: Close` to control this behaviour.",
								"allowedToToggle": true,
								"disableEdit": true,
								"key": "Connection",
								"value": "keep-alive",
								"system": true,
								"type": "text"
							},
							{
								"key": "Authorization",
								"value": "Bearer {{lenra_access_token}}",
								"type": "text",
								"id": 0
							}
						],
						"url": {
							"raw": "{{lenra_endpoint}}/api/me/apps",
							"host": [
								"{{lenra_endpoint}}"
							],
							"path": [
								"api",
								"me",
								"apps"
							]
						}
					},
					"response": []
				},
				{
					"name": "list_environments",
					"event": [
						{
							"listen": "test",
							"script": {
								"exec": [
									"pm.test(\"Status code is 200\", function () {\r",
									"    pm.response.to.have.status(200);\r",
									"});\r",
									"\r",
									"pm.test(\"Has some envs\", function () {\r",
									"    var jsonData = pm.response.json();\r",
									"    pm.expect(jsonData).to.be.an(\"array\")\r",
									"    const last_env = jsonData.last()\r",
									"    pm.expect(last_env).not.to.be.an(\"undefined\");\r",
									"    pm.collectionVariables.set(\"lenra_latest_created_env\", last_env.id);\r",
									"});\r",
									""
								],
								"type": "text/javascript"
							}
						}
					],
					"request": {
						"method": "GET",
						"header": [
							{
								"name": "cache-control",
								"sortOrder": 2,
								"infoTitle": "We recommend using this header",
								"info": "Postman added \"Cache-Control: no-cache\" as a precautionary measure to prevent the server from returning stale response when one makes repeated requests.\n\nYou can remove this header in the app settings or enter a new one with a different value.",
								"allowedToToggle": false,
								"disableEdit": true,
								"previewSettingsLink": "Go to settings",
								"key": "Cache-Control",
								"value": "no-cache",
								"system": true,
								"type": "text"
							},
							{
								"name": "postman-token",
								"sortOrder": 3,
								"infoTitle": "We recommend using this header",
								"info": "The Postman-Token header appends a random UUID to every outgoing request. Postman adds this header for API developers to better debug requests sent and to ensure separate requests appear distinct to the receiving server.\n\nYou can remove this header in the app settings.",
								"allowedToToggle": false,
								"disableEdit": true,
								"previewSettingsLink": "Go to settings",
								"key": "Postman-Token",
								"value": "<calculated when request is sent>",
								"system": true,
								"type": "text"
							},
							{
								"name": "host",
								"sortOrder": 6,
								"infoTitle": "We recommend using this header",
								"info": "The Host header is added to identify the domain name for which a request is being sent to the server. This header is implicitly sent by every HTTP client.\n\nYou can remove the header or enter a new one with a different value. It is most likely that without this header, your request will return an HTTP 400 error.",
								"allowedToToggle": true,
								"disableEdit": true,
								"key": "Host",
								"value": "<calculated when request is sent>",
								"system": true,
								"type": "text"
							},
							{
								"name": "user-agent",
								"sortOrder": 7,
								"infoTitle": "We recommend using this header",
								"info": "The User-Agent header is added to help the server identify Postman as the HTTP requesting application or client.\n\nIt is recommended that this header be sent, but you can remove the header or enter a new one with a different value.",
								"allowedToToggle": true,
								"disableEdit": true,
								"key": "User-Agent",
								"value": "PostmanRuntime/7.32.1",
								"system": true,
								"type": "text"
							},
							{
								"name": "accept",
								"sortOrder": 8,
								"infoTitle": "We recommend using this header",
								"info": "The \"Accept: */*\" header is added to tell the server that Postman can understand and process all forms of response content types.\n\nIt is recommended that this header be sent, but you can remove the header or enter a new one with a different value.",
								"allowedToToggle": true,
								"disableEdit": true,
								"key": "Accept",
								"value": "*/*",
								"system": true,
								"type": "text"
							},
							{
								"name": "accept-encoding",
								"sortOrder": 9,
								"infoTitle": "We recommend using this header",
								"info": "The Accept-Encoding header is added to indicate to the server that Postman HTTP client supports a defined list of content-encoding or compression algorithms as response.\n\nYou can remove the header or enter a new one with a different value. Doing that may not accurately render the response within the app.",
								"allowedToToggle": true,
								"disableEdit": true,
								"key": "Accept-Encoding",
								"value": "gzip, deflate, br",
								"system": true,
								"type": "text"
							},
							{
								"name": "connection",
								"sortOrder": 10,
								"infoTitle": "We recommend using this header",
								"info": "Postman added the Connection header to indicate the server to keep the underlying network connection open once the current response is received. This allows Postman to reuse the same connection for faster response times in subsequent requests to the same server.\n\nYou can remove this header or enter a new one with a different value, such as `Connection: Close` to control this behaviour.",
								"allowedToToggle": true,
								"disableEdit": true,
								"key": "Connection",
								"value": "keep-alive",
								"system": true,
								"type": "text"
							},
							{
								"key": "Authorization",
								"value": "Bearer {{lenra_access_token}}",
								"type": "text",
								"id": 0
							}
						],
						"url": {
							"raw": "{{lenra_endpoint}}/api/apps/:app_id/environments",
							"host": [
								"{{lenra_endpoint}}"
							],
							"path": [
								"api",
								"apps",
								":app_id",
								"environments"
							],
							"variable": [
								{
									"id": 0,
									"key": "app_id",
									"value": "{{lenra_latest_created_app}}",
									"type": "string"
								}
							]
						}
					},
					"response": []
				},
				{
					"name": "list_environments_secrets",
					"event": [
						{
							"listen": "test",
							"script": {
								"exec": [
									"pm.test(\"Status code is 200\", function () {\r",
									"    pm.response.to.have.status(200);\r",
									"});\r",
									"\r",
									"pm.test(\"Has some secrets\", function () {\r",
									"    var jsonData = pm.response.json();\r",
									"    pm.expect(jsonData).to.be.an(\"array\")\r",
									"    const last_secret = jsonData.last()\r",
									"    pm.expect(last_secret).not.to.be.an(\"undefined\");\r",
									"    pm.collectionVariables.set(\"lenra_latest_created_secret\", last_secret.id);\r",
									"});\r",
									""
								],
								"type": "text/javascript"
							}
						}
					],
					"request": {
						"method": "GET",
						"header": [
							{
								"name": "cache-control",
								"sortOrder": 2,
								"infoTitle": "We recommend using this header",
								"info": "Postman added \"Cache-Control: no-cache\" as a precautionary measure to prevent the server from returning stale response when one makes repeated requests.\n\nYou can remove this header in the app settings or enter a new one with a different value.",
								"allowedToToggle": false,
								"disableEdit": true,
								"previewSettingsLink": "Go to settings",
								"key": "Cache-Control",
								"value": "no-cache",
								"system": true,
								"type": "text"
							},
							{
								"name": "postman-token",
								"sortOrder": 3,
								"infoTitle": "We recommend using this header",
								"info": "The Postman-Token header appends a random UUID to every outgoing request. Postman adds this header for API developers to better debug requests sent and to ensure separate requests appear distinct to the receiving server.\n\nYou can remove this header in the app settings.",
								"allowedToToggle": false,
								"disableEdit": true,
								"previewSettingsLink": "Go to settings",
								"key": "Postman-Token",
								"value": "<calculated when request is sent>",
								"system": true,
								"type": "text"
							},
							{
								"name": "host",
								"sortOrder": 6,
								"infoTitle": "We recommend using this header",
								"info": "The Host header is added to identify the domain name for which a request is being sent to the server. This header is implicitly sent by every HTTP client.\n\nYou can remove the header or enter a new one with a different value. It is most likely that without this header, your request will return an HTTP 400 error.",
								"allowedToToggle": true,
								"disableEdit": true,
								"key": "Host",
								"value": "<calculated when request is sent>",
								"system": true,
								"type": "text"
							},
							{
								"name": "user-agent",
								"sortOrder": 7,
								"infoTitle": "We recommend using this header",
								"info": "The User-Agent header is added to help the server identify Postman as the HTTP requesting application or client.\n\nIt is recommended that this header be sent, but you can remove the header or enter a new one with a different value.",
								"allowedToToggle": true,
								"disableEdit": true,
								"key": "User-Agent",
								"value": "PostmanRuntime/7.32.1",
								"system": true,
								"type": "text"
							},
							{
								"name": "accept",
								"sortOrder": 8,
								"infoTitle": "We recommend using this header",
								"info": "The \"Accept: */*\" header is added to tell the server that Postman can understand and process all forms of response content types.\n\nIt is recommended that this header be sent, but you can remove the header or enter a new one with a different value.",
								"allowedToToggle": true,
								"disableEdit": true,
								"key": "Accept",
								"value": "*/*",
								"system": true,
								"type": "text"
							},
							{
								"name": "accept-encoding",
								"sortOrder": 9,
								"infoTitle": "We recommend using this header",
								"info": "The Accept-Encoding header is added to indicate to the server that Postman HTTP client supports a defined list of content-encoding or compression algorithms as response.\n\nYou can remove the header or enter a new one with a different value. Doing that may not accurately render the response within the app.",
								"allowedToToggle": true,
								"disableEdit": true,
								"key": "Accept-Encoding",
								"value": "gzip, deflate, br",
								"system": true,
								"type": "text"
							},
							{
								"name": "connection",
								"sortOrder": 10,
								"infoTitle": "We recommend using this header",
								"info": "Postman added the Connection header to indicate the server to keep the underlying network connection open once the current response is received. This allows Postman to reuse the same connection for faster response times in subsequent requests to the same server.\n\nYou can remove this header or enter a new one with a different value, such as `Connection: Close` to control this behaviour.",
								"allowedToToggle": true,
								"disableEdit": true,
								"key": "Connection",
								"value": "keep-alive",
								"system": true,
								"type": "text"
							},
							{
								"key": "Authorization",
								"value": "Bearer {{lenra_access_token}}",
								"type": "text",
								"id": 0
							}
						],
						"url": {
							"raw": "{{lenra_endpoint}}/api/apps/:app_id/environments/:env_id/secrets",
							"host": [
								"{{lenra_endpoint}}"
							],
							"path": [
								"api",
								"apps",
								":app_id",
								"environments",
								":env_id",
								"secrets"
							],
							"variable": [
								{
									"id": 0,
									"key": "app_id",
									"value": "{{lenra_latest_created_app}}",
									"type": "string"
								},
								{
									"key": "env_id",
									"value": "{{lenra_latest_created_env}}",
									"type": "string"
								}
							]
						}
					},
					"response": []
				},
				{
					"name": "add_environments_secrets",
					"event": [
						{
							"listen": "test",
							"script": {
								"exec": [
									"pm.test(\"Status code is 200\", function () {\r",
									"    pm.response.to.have.status(200);\r",
									"});\r",
									"\r",
									"pm.test(\"Secret is created\", function () {\r",
									"    var jsonData = pm.response.json();\r",
									"    const {id, key} = jsonData\r",
									"    pm.expect(id).to.be.a(\"number\")\r",
									"    pm.collectionVariables.set(\"lenra_latest_created_secret\", id);\r",
									"    pm.collectionVariables.set(\"lenra_latest_created_secret_key\", key);\r",
									"});\r",
									""
								],
								"type": "text/javascript"
							}
						}
					],
					"request": {
						"method": "POST",
						"header": [
							{
								"name": "cache-control",
								"sortOrder": 2,
								"infoTitle": "We recommend using this header",
								"info": "Postman added \"Cache-Control: no-cache\" as a precautionary measure to prevent the server from returning stale response when one makes repeated requests.\n\nYou can remove this header in the app settings or enter a new one with a different value.",
								"allowedToToggle": false,
								"disableEdit": true,
								"previewSettingsLink": "Go to settings",
								"key": "Cache-Control",
								"value": "no-cache",
								"system": true,
								"type": "text"
							},
							{
								"name": "postman-token",
								"sortOrder": 3,
								"infoTitle": "We recommend using this header",
								"info": "The Postman-Token header appends a random UUID to every outgoing request. Postman adds this header for API developers to better debug requests sent and to ensure separate requests appear distinct to the receiving server.\n\nYou can remove this header in the app settings.",
								"allowedToToggle": false,
								"disableEdit": true,
								"previewSettingsLink": "Go to settings",
								"key": "Postman-Token",
								"value": "<calculated when request is sent>",
								"system": true,
								"type": "text"
							},
							{
								"name": "host",
								"sortOrder": 6,
								"infoTitle": "We recommend using this header",
								"info": "The Host header is added to identify the domain name for which a request is being sent to the server. This header is implicitly sent by every HTTP client.\n\nYou can remove the header or enter a new one with a different value. It is most likely that without this header, your request will return an HTTP 400 error.",
								"allowedToToggle": true,
								"disableEdit": true,
								"key": "Host",
								"value": "<calculated when request is sent>",
								"system": true,
								"type": "text"
							},
							{
								"name": "user-agent",
								"sortOrder": 7,
								"infoTitle": "We recommend using this header",
								"info": "The User-Agent header is added to help the server identify Postman as the HTTP requesting application or client.\n\nIt is recommended that this header be sent, but you can remove the header or enter a new one with a different value.",
								"allowedToToggle": true,
								"disableEdit": true,
								"key": "User-Agent",
								"value": "PostmanRuntime/7.32.1",
								"system": true,
								"type": "text"
							},
							{
								"name": "accept",
								"sortOrder": 8,
								"infoTitle": "We recommend using this header",
								"info": "The \"Accept: */*\" header is added to tell the server that Postman can understand and process all forms of response content types.\n\nIt is recommended that this header be sent, but you can remove the header or enter a new one with a different value.",
								"allowedToToggle": true,
								"disableEdit": true,
								"key": "Accept",
								"value": "*/*",
								"system": true,
								"type": "text"
							},
							{
								"name": "accept-encoding",
								"sortOrder": 9,
								"infoTitle": "We recommend using this header",
								"info": "The Accept-Encoding header is added to indicate to the server that Postman HTTP client supports a defined list of content-encoding or compression algorithms as response.\n\nYou can remove the header or enter a new one with a different value. Doing that may not accurately render the response within the app.",
								"allowedToToggle": true,
								"disableEdit": true,
								"key": "Accept-Encoding",
								"value": "gzip, deflate, br",
								"system": true,
								"type": "text"
							},
							{
								"name": "connection",
								"sortOrder": 10,
								"infoTitle": "We recommend using this header",
								"info": "Postman added the Connection header to indicate the server to keep the underlying network connection open once the current response is received. This allows Postman to reuse the same connection for faster response times in subsequent requests to the same server.\n\nYou can remove this header or enter a new one with a different value, such as `Connection: Close` to control this behaviour.",
								"allowedToToggle": true,
								"disableEdit": true,
								"key": "Connection",
								"value": "keep-alive",
								"system": true,
								"type": "text"
							},
							{
								"key": "Authorization",
								"value": "Bearer {{lenra_access_token}}",
								"type": "text",
								"id": 0
							}
						],
						"body": {
							"mode": "urlencoded",
							"urlencoded": [
								{
									"key": "key",
									"value": "test",
									"type": "text"
								},
								{
									"key": "value",
									"value": "test",
									"type": "text"
								}
							]
						},
						"url": {
							"raw": "{{lenra_endpoint}}/api/apps/:app_id/environments/:env_id/secrets",
							"host": [
								"{{lenra_endpoint}}"
							],
							"path": [
								"api",
								"apps",
								":app_id",
								"environments",
								":env_id",
								"secrets"
							],
							"variable": [
								{
									"id": 0,
									"key": "app_id",
									"value": "{{lenra_latest_created_app}}",
									"type": "string"
								},
								{
									"key": "env_id",
									"value": "{{lenra_latest_created_env}}",
									"type": "string"
								}
							]
						}
					},
					"response": []
				},
				{
					"name": "update_environments_secrets",
					"event": [
						{
							"listen": "test",
							"script": {
								"exec": [
									"pm.test(\"Status code is 200\", function () {\r",
									"    pm.response.to.have.status(200);\r",
									"});\r",
									"\r",
									"pm.test(\"Secret is created\", function () {\r",
									"    var jsonData = pm.response.json();\r",
									"    const id = jsonData.id\r",
									"    pm.expect(id).to.be.a(\"number\")\r",
									"    pm.collectionVariables.set(\"lenra_latest_created_secret\", id);\r",
									"});\r",
									""
								],
								"type": "text/javascript"
							}
						}
					],
					"request": {
						"method": "PUT",
						"header": [
							{
								"name": "cache-control",
								"sortOrder": 2,
								"infoTitle": "We recommend using this header",
								"info": "Postman added \"Cache-Control: no-cache\" as a precautionary measure to prevent the server from returning stale response when one makes repeated requests.\n\nYou can remove this header in the app settings or enter a new one with a different value.",
								"allowedToToggle": false,
								"disableEdit": true,
								"previewSettingsLink": "Go to settings",
								"key": "Cache-Control",
								"value": "no-cache",
								"system": true,
								"type": "text"
							},
							{
								"name": "postman-token",
								"sortOrder": 3,
								"infoTitle": "We recommend using this header",
								"info": "The Postman-Token header appends a random UUID to every outgoing request. Postman adds this header for API developers to better debug requests sent and to ensure separate requests appear distinct to the receiving server.\n\nYou can remove this header in the app settings.",
								"allowedToToggle": false,
								"disableEdit": true,
								"previewSettingsLink": "Go to settings",
								"key": "Postman-Token",
								"value": "<calculated when request is sent>",
								"system": true,
								"type": "text"
							},
							{
								"name": "host",
								"sortOrder": 6,
								"infoTitle": "We recommend using this header",
								"info": "The Host header is added to identify the domain name for which a request is being sent to the server. This header is implicitly sent by every HTTP client.\n\nYou can remove the header or enter a new one with a different value. It is most likely that without this header, your request will return an HTTP 400 error.",
								"allowedToToggle": true,
								"disableEdit": true,
								"key": "Host",
								"value": "<calculated when request is sent>",
								"system": true,
								"type": "text"
							},
							{
								"name": "user-agent",
								"sortOrder": 7,
								"infoTitle": "We recommend using this header",
								"info": "The User-Agent header is added to help the server identify Postman as the HTTP requesting application or client.\n\nIt is recommended that this header be sent, but you can remove the header or enter a new one with a different value.",
								"allowedToToggle": true,
								"disableEdit": true,
								"key": "User-Agent",
								"value": "PostmanRuntime/7.32.1",
								"system": true,
								"type": "text"
							},
							{
								"name": "accept",
								"sortOrder": 8,
								"infoTitle": "We recommend using this header",
								"info": "The \"Accept: */*\" header is added to tell the server that Postman can understand and process all forms of response content types.\n\nIt is recommended that this header be sent, but you can remove the header or enter a new one with a different value.",
								"allowedToToggle": true,
								"disableEdit": true,
								"key": "Accept",
								"value": "*/*",
								"system": true,
								"type": "text"
							},
							{
								"name": "accept-encoding",
								"sortOrder": 9,
								"infoTitle": "We recommend using this header",
								"info": "The Accept-Encoding header is added to indicate to the server that Postman HTTP client supports a defined list of content-encoding or compression algorithms as response.\n\nYou can remove the header or enter a new one with a different value. Doing that may not accurately render the response within the app.",
								"allowedToToggle": true,
								"disableEdit": true,
								"key": "Accept-Encoding",
								"value": "gzip, deflate, br",
								"system": true,
								"type": "text"
							},
							{
								"name": "connection",
								"sortOrder": 10,
								"infoTitle": "We recommend using this header",
								"info": "Postman added the Connection header to indicate the server to keep the underlying network connection open once the current response is received. This allows Postman to reuse the same connection for faster response times in subsequent requests to the same server.\n\nYou can remove this header or enter a new one with a different value, such as `Connection: Close` to control this behaviour.",
								"allowedToToggle": true,
								"disableEdit": true,
								"key": "Connection",
								"value": "keep-alive",
								"system": true,
								"type": "text"
							},
							{
								"key": "Authorization",
								"value": "Bearer {{lenra_access_token}}",
								"type": "text",
								"id": 0
							}
						],
						"body": {
							"mode": "urlencoded",
							"urlencoded": [
								{
									"key": "key",
									"value": "test",
									"type": "text"
								},
								{
									"key": "value",
									"value": "test",
									"type": "text"
								}
							]
						},
						"url": {
							"raw": "{{lenra_endpoint}}/api/apps/:app_id/environments/:env_id/secrets/:key",
							"host": [
								"{{lenra_endpoint}}"
							],
							"path": [
								"api",
								"apps",
								":app_id",
								"environments",
								":env_id",
								"secrets",
								":key"
							],
							"variable": [
								{
									"id": 0,
									"key": "app_id",
									"value": "{{lenra_latest_created_app}}",
									"type": "string"
								},
								{
									"key": "env_id",
									"value": "{{lenra_latest_created_env}}",
									"type": "string"
								},
								{
									"key": "key",
									"value": "{{lenra_latest_created_secret_key}}",
									"type": "string"
								}
							]
						}
					},
					"response": []
				},
				{
					"name": "current_dev_list_app",
					"event": [
						{
							"listen": "test",
							"script": {
								"exec": [
									"pm.test(\"Status code is 200\", function () {\r",
									"    pm.response.to.have.status(200);\r",
									"});\r",
									"\r",
									"pm.test(\"Has some apps\", function () {\r",
									"    var jsonData = pm.response.json();\r",
									"    pm.expect(jsonData).to.be.an(\"array\")\r",
									"    const last_app = jsonData.last()\r",
									"    pm.expect(last_app).not.to.be.an(\"undefined\");\r",
									"    pm.collectionVariables.set(\"lenra_latest_created_app\", last_app.id);\r",
									"});\r",
									""
								],
								"type": "text/javascript"
							}
						}
					],
					"request": {
						"method": "GET",
						"header": [
							{
								"name": "cache-control",
								"sortOrder": 2,
								"infoTitle": "We recommend using this header",
								"info": "Postman added \"Cache-Control: no-cache\" as a precautionary measure to prevent the server from returning stale response when one makes repeated requests.\n\nYou can remove this header in the app settings or enter a new one with a different value.",
								"allowedToToggle": false,
								"disableEdit": true,
								"previewSettingsLink": "Go to settings",
								"key": "Cache-Control",
								"value": "no-cache",
								"system": true,
								"type": "text"
							},
							{
								"name": "postman-token",
								"sortOrder": 3,
								"infoTitle": "We recommend using this header",
								"info": "The Postman-Token header appends a random UUID to every outgoing request. Postman adds this header for API developers to better debug requests sent and to ensure separate requests appear distinct to the receiving server.\n\nYou can remove this header in the app settings.",
								"allowedToToggle": false,
								"disableEdit": true,
								"previewSettingsLink": "Go to settings",
								"key": "Postman-Token",
								"value": "<calculated when request is sent>",
								"system": true,
								"type": "text"
							},
							{
								"name": "host",
								"sortOrder": 6,
								"infoTitle": "We recommend using this header",
								"info": "The Host header is added to identify the domain name for which a request is being sent to the server. This header is implicitly sent by every HTTP client.\n\nYou can remove the header or enter a new one with a different value. It is most likely that without this header, your request will return an HTTP 400 error.",
								"allowedToToggle": true,
								"disableEdit": true,
								"key": "Host",
								"value": "<calculated when request is sent>",
								"system": true,
								"type": "text"
							},
							{
								"name": "user-agent",
								"sortOrder": 7,
								"infoTitle": "We recommend using this header",
								"info": "The User-Agent header is added to help the server identify Postman as the HTTP requesting application or client.\n\nIt is recommended that this header be sent, but you can remove the header or enter a new one with a different value.",
								"allowedToToggle": true,
								"disableEdit": true,
								"key": "User-Agent",
								"value": "PostmanRuntime/7.32.1",
								"system": true,
								"type": "text"
							},
							{
								"name": "accept",
								"sortOrder": 8,
								"infoTitle": "We recommend using this header",
								"info": "The \"Accept: */*\" header is added to tell the server that Postman can understand and process all forms of response content types.\n\nIt is recommended that this header be sent, but you can remove the header or enter a new one with a different value.",
								"allowedToToggle": true,
								"disableEdit": true,
								"key": "Accept",
								"value": "*/*",
								"system": true,
								"type": "text"
							},
							{
								"name": "accept-encoding",
								"sortOrder": 9,
								"infoTitle": "We recommend using this header",
								"info": "The Accept-Encoding header is added to indicate to the server that Postman HTTP client supports a defined list of content-encoding or compression algorithms as response.\n\nYou can remove the header or enter a new one with a different value. Doing that may not accurately render the response within the app.",
								"allowedToToggle": true,
								"disableEdit": true,
								"key": "Accept-Encoding",
								"value": "gzip, deflate, br",
								"system": true,
								"type": "text"
							},
							{
								"name": "connection",
								"sortOrder": 10,
								"infoTitle": "We recommend using this header",
								"info": "Postman added the Connection header to indicate the server to keep the underlying network connection open once the current response is received. This allows Postman to reuse the same connection for faster response times in subsequent requests to the same server.\n\nYou can remove this header or enter a new one with a different value, such as `Connection: Close` to control this behaviour.",
								"allowedToToggle": true,
								"disableEdit": true,
								"key": "Connection",
								"value": "keep-alive",
								"system": true,
								"type": "text"
							},
							{
								"key": "Authorization",
								"value": "Bearer {{lenra_access_token}}",
								"type": "text",
								"id": 0
							}
						],
						"url": {
							"raw": "{{lenra_endpoint}}/api/me/apps",
							"host": [
								"{{lenra_endpoint}}"
							],
							"path": [
								"api",
								"me",
								"apps"
							]
						}
					},
					"response": []
				}
			]
		}
	],
	"variable": [
		{
			"key": "lenra_endpoint",
			"value": "http://localhost:4000",
			"type": "string"
		},
		{
			"key": "hydra_endpoint",
			"value": "http://localhost:4444",
			"type": "string"
		},
		{
			"key": "hydra_auth_code",
			"value": "",
			"type": "string"
		},
		{
			"key": "lenra_client_id",
			"value": "",
			"type": "string"
		},
		{
			"key": "hydra_redirect_url",
			"value": "https://oauthdebugger.com/debug",
			"type": "string"
		},
		{
			"key": "hydra_client_scope",
			"value": "profile store manage:account manage:apps",
			"type": "string"
		},
		{
			"key": "lenra_access_token",
			"value": "",
			"type": "string"
		},
		{
			"key": "lenra_latest_created_app",
			"value": "",
			"type": "default"
		},
		{
			"key": "lenra_latest_created_env",
			"value": "",
			"type": "default"
		},
		{
			"key": "lenra-intra",
			"value": "",
			"type": "string"
		}
	]
}
